{
  "updated_at": "2026-03-28T07:00:00+09:00",
  "master_switch": {
    "qqq_price": 587.82,
    "qqq_ma200": 592.43,
    "qqq_above_ma200": false,
    "spy_price": 645.09,
    "spy_ma200": 657.19,
    "spy_above_ma200": false,
    "status": "RED"
  },
  "macro": {
    "vix": 30.91,
    "vix_tier": "extreme",
    "treasury_30y": 4.982,
    "usdkrw": 1425.5
  },
  "tickers": {
    "VOO": {
      "price": 583.50,
      "ma20": 598.20,
      "ma50": 612.40,
      "ma200": 570.30,
      "above_ma200": true,
      "rsi": 38.5,
      "macd": -4.20,
      "macd_signal": -2.80,
      "macd_histogram": -1.40,
      "macd_hist_trend": "declining_2d",
      "bb_upper": 625.0,
      "bb_lower": 571.4,
      "adx": 22.3,
      "volume": 3500000,
      "volume_avg20": 4200000,
      "volume_ratio": 0.83
    },
    "BIL": {
      "price": 89.89,
      "ma20": 89.85,
      "ma50": 89.80,
      "ma200": 89.70,
      "above_ma200": true,
      "rsi": 52.0,
      "macd": 0.02,
      "macd_signal": 0.01,
      "macd_histogram": 0.01,
      "macd_hist_trend": "rising_2d",
      "bb_upper": 89.95,
      "bb_lower": 89.75,
      "adx": 8.5,
      "volume": 8500000,
      "volume_avg20": 9000000,
      "volume_ratio": 0.94
    },
    "QQQ": {
      "price": 587.82,
      "ma20": 608.50,
      "ma50": 625.30,
      "ma200": 592.43,
      "above_ma200": false,
      "rsi": 36.2,
      "macd": -8.50,
      "macd_signal": -5.20,
      "macd_histogram": -3.30,
      "macd_hist_trend": "declining_2d",
      "bb_upper": 640.0,
      "bb_lower": 577.0,
      "adx": 28.4,
      "volume": 45000000,
      "volume_avg20": 52000000,
      "volume_ratio": 0.87
    },
    "TSLA": {
      "price": 361.88,
      "ma20": 378.50,
      "ma50": 395.20,
      "ma200": 310.00,
      "above_ma200": true,
      "rsi": 38.2,
      "macd": -3.44,
      "macd_signal": -1.82,
      "macd_histogram": -1.62,
      "macd_hist_trend": "declining_2d",
      "bb_upper": 410.50,
      "bb_lower": 346.50,
      "adx": 28.5,
      "volume": 45000000,
      "volume_avg20": 52000000,
      "volume_ratio": 0.87
    },
    "NVDA": {
      "price": 131.38,
      "ma20": 142.50,
      "ma50": 155.30,
      "ma200": 118.20,
      "above_ma200": true,
      "rsi": 34.8,
      "macd": -5.20,
      "macd_signal": -3.10,
      "macd_histogram": -2.10,
      "macd_hist_trend": "declining_2d",
      "bb_upper": 158.0,
      "bb_lower": 127.0,
      "adx": 32.1,
      "volume": 280000000,
      "volume_avg20": 310000000,
      "volume_ratio": 0.90
    },
    "TLT": {
      "price": 91.45,
      "ma20": 93.20,
      "ma50": 94.80,
      "ma200": 92.10,
      "above_ma200": false,
      "rsi": 38.5,
      "macd": -0.85,
      "macd_signal": -0.42,
      "macd_histogram": -0.43,
      "macd_hist_trend": "declining_2d",
      "bb_upper": 96.5,
      "bb_lower": 89.9,
      "adx": 18.2,
      "volume": 18000000,
      "volume_avg20": 20000000,
      "volume_ratio": 0.90
    },
    "SLV": {
      "price": 28.80,
      "ma20": 28.20,
      "ma50": 27.50,
      "ma200": 25.80,
      "above_ma200": true,
      "rsi": 58.4,
      "macd": 0.42,
      "macd_signal": 0.28,
      "macd_histogram": 0.14,
      "macd_hist_trend": "rising_2d",
      "bb_upper": 30.5,
      "bb_lower": 25.9,
      "adx": 24.8,
      "volume": 15000000,
      "volume_avg20": 14000000,
      "volume_ratio": 1.07
    }
  }
}
