{
  "updated_at": "2026-03-28T07:00:00+09:00",
  "source": "initial_manual",
  "total_value_usd": 431847.0,
  "holdings": [
    {
      "ticker": "VOO",
      "value_usd": 102110.0,
      "pnl_usd": 12079.06,
      "pnl_pct": 13.42,
      "shares": 175.157486
    },
    {
      "ticker": "BIL",
      "value_usd": 91630.0,
      "pnl_usd": 430.50,
      "pnl_pct": 0.47,
      "shares": 1019.2
    },
    {
      "ticker": "QQQ",
      "value_usd": 76310.0,
      "pnl_usd": 8240.0,
      "pnl_pct": 12.10,
      "shares": 129.803
    },
    {
      "ticker": "SCHD",
      "value_usd": 46025.0,
      "pnl_usd": 3850.0,
      "pnl_pct": 9.12,
      "shares": 751.22
    },
    {
      "ticker": "AAPL",
      "value_usd": 19742.0,
      "pnl_usd": 2310.0,
      "pnl_pct": 13.24,
      "shares": 90.15
    },
    {
      "ticker": "O",
      "value_usd": 17056.0,
      "pnl_usd": -892.0,
      "pnl_pct": -4.97,
      "shares": 295.8
    },
    {
      "ticker": "JEPI",
      "value_usd": 14113.0,
      "pnl_usd": 680.0,
      "pnl_pct": 5.07,
      "shares": 216.82
    },
    {
      "ticker": "SOXX",
      "value_usd": 9992.0,
      "pnl_usd": -1240.0,
      "pnl_pct": -11.04,
      "shares": 42.35
    },
    {
      "ticker": "TSLA",
      "value_usd": 9745.0,
      "pnl_usd": -3280.0,
      "pnl_pct": -25.19,
      "shares": 26.93
    },
    {
      "ticker": "TLT",
      "value_usd": 8564.0,
      "pnl_usd": -1820.0,
      "pnl_pct": -17.53,
      "shares": 93.64
    },
    {
      "ticker": "NVDA",
      "value_usd": 8158.0,
      "pnl_usd": -2140.0,
      "pnl_pct": -20.77,
      "shares": 62.12
    },
    {
      "ticker": "PLTR",
      "value_usd": 8130.0,
      "pnl_usd": 3420.0,
      "pnl_pct": 72.61,
      "shares": 87.42
    },
    {
      "ticker": "SPY",
      "value_usd": 5635.0,
      "pnl_usd": 420.0,
      "pnl_pct": 8.05,
      "shares": 8.73
    },
    {
      "ticker": "UNH",
      "value_usd": 4662.0,
      "pnl_usd": -890.0,
      "pnl_pct": -16.02,
      "shares": 9.82
    },
    {
      "ticker": "MSFT",
      "value_usd": 4281.0,
      "pnl_usd": -540.0,
      "pnl_pct": -11.20,
      "shares": 10.25
    },
    {
      "ticker": "GOOGL",
      "value_usd": 2929.0,
      "pnl_usd": -310.0,
      "pnl_pct": -9.57,
      "shares": 18.34
    },
    {
      "ticker": "AMZN",
      "value_usd": 1166.0,
      "pnl_usd": -180.0,
      "pnl_pct": -13.38,
      "shares": 6.12
    },
    {
      "ticker": "SLV",
      "value_usd": 761.0,
      "pnl_usd": 85.0,
      "pnl_pct": 12.57,
      "shares": 26.43
    },
    {
      "ticker": "TQQQ",
      "value_usd": 290.0,
      "pnl_usd": -420.0,
      "pnl_pct": -59.15,
      "shares": 14.82
    },
    {
      "ticker": "SOXL",
      "value_usd": 233.0,
      "pnl_usd": -380.0,
      "pnl_pct": -62.03,
      "shares": 41.25
    },
    {
      "ticker": "ETHU",
      "value_usd": 202.0,
      "pnl_usd": -280.0,
      "pnl_pct": -58.10,
      "shares": 12.64
    },
    {
      "ticker": "CRCL",
      "value_usd": 94.0,
      "pnl_usd": -18.0,
      "pnl_pct": -16.07,
      "shares": 1.65
    },
    {
      "ticker": "BTDR",
      "value_usd": 18.0,
      "pnl_usd": -32.0,
      "pnl_pct": -64.0,
      "shares": 2.1
    }
  ]
}
